odoo/addons/partner_pricelist_tracking/README.rst
odoo/addons/partner_pricelist_tracking/__init__.py
odoo/addons/partner_pricelist_tracking/__manifest__.py
odoo/addons/partner_pricelist_tracking/i18n/es.po
odoo/addons/partner_pricelist_tracking/i18n/partner_pricelist_tracking.pot
odoo/addons/partner_pricelist_tracking/models/__init__.py
odoo/addons/partner_pricelist_tracking/models/res_partner.py
odoo/addons/partner_pricelist_tracking/readme/CONFIGURE.rst
odoo/addons/partner_pricelist_tracking/readme/CONTRIBUTORS.rst
odoo/addons/partner_pricelist_tracking/readme/DESCRIPTION.rst
odoo/addons/partner_pricelist_tracking/readme/ROADMAP.rst
odoo/addons/partner_pricelist_tracking/static/description/icon.png
odoo/addons/partner_pricelist_tracking/static/description/index.html
odoo_addon_partner_pricelist_tracking-15.0.1.0.0.5.dist-info/METADATA
odoo_addon_partner_pricelist_tracking-15.0.1.0.0.5.dist-info/WHEEL
odoo_addon_partner_pricelist_tracking-15.0.1.0.0.5.dist-info/top_level.txt
odoo_addon_partner_pricelist_tracking-15.0.1.0.0.5.dist-info/RECORD
